pyeden/__init__.py
pyeden/pyeden.py
pyeden-0.1.0.dist-info/LICENCE
pyeden-0.1.0.dist-info/METADATA
pyeden-0.1.0.dist-info/WHEEL
pyeden-0.1.0.dist-info/top_level.txt
pyeden-0.1.0.dist-info/RECORD
